imantics/__init__.py
imantics/annotation.py
imantics/basic.py
imantics/category.py
imantics/color.py
imantics/dataset.py
imantics/image.py
imantics/point.py
imantics/styles.py
imantics/utils.py
imantics-0.1.0.dist-info/DESCRIPTION.rst
imantics-0.1.0.dist-info/METADATA
imantics-0.1.0.dist-info/RECORD
imantics-0.1.0.dist-info/WHEEL
imantics-0.1.0.dist-info/metadata.json
imantics-0.1.0.dist-info/top_level.txt
