Metadata-Version: 2.0
Name: imantics
Version: 0.1.0
Summary: Python package for managing image annotations
Home-page: https://github.com/jsbroks/imantics
Author: Justin Brooks
Author-email: jsbroks@gmail.com
License: MIT
Platform: UNKNOWN
Requires-Dist: numpy
Requires-Dist: opencv-python (>=3)
Requires-Dist: lxml
